[
  {
    "page_number": 176,
    "line_number": 1,
    "surah_number": 7,
    "ayah_number": 196,
    "position": 1,
    "min_x": 55,
    "max_x": 986,
    "min_y": 26,
    "max_y": 116
  },
  {
    "page_number": 176,
    "line_number": 2,
    "surah_number": 7,
    "ayah_number": 197,
    "position": 1,
    "min_x": 55,
    "max_x": 986,
    "min_y": 141,
    "max_y": 224
  },
  {
    "page_number": 176,
    "line_number": 3,
    "surah_number": 7,
    "ayah_number": 197,
    "position": 2,
    "min_x": 592,
    "max_x": 986,
    "min_y": 237,
    "max_y": 333
  },
  {
    "page_number": 176,
    "line_number": 3,
    "surah_number": 7,
    "ayah_number": 198,
    "position": 1,
    "min_x": 55,
    "max_x": 592,
    "min_y": 237,
    "max_y": 333
  },
  {
    "page_number": 176,
    "line_number": 4,
    "surah_number": 7,
    "ayah_number": 198,
    "position": 2,
    "min_x": 275,
    "max_x": 986,
    "min_y": 354,
    "max_y": 441
  },
  {
    "page_number": 176,
    "line_number": 4,
    "surah_number": 7,
    "ayah_number": 199,
    "position": 1,
    "min_x": 55,
    "max_x": 275,
    "min_y": 354,
    "max_y": 441
  },
  {
    "page_number": 176,
    "line_number": 5,
    "surah_number": 7,
    "ayah_number": 199,
    "position": 2,
    "min_x": 362,
    "max_x": 986,
    "min_y": 463,
    "max_y": 549
  },
  {
    "page_number": 176,
    "line_number": 5,
    "surah_number": 7,
    "ayah_number": 200,
    "position": 1,
    "min_x": 55,
    "max_x": 362,
    "min_y": 463,
    "max_y": 549
  },
  {
    "page_number": 176,
    "line_number": 6,
    "surah_number": 7,
    "ayah_number": 200,
    "position": 2,
    "min_x": 140,
    "max_x": 986,
    "min_y": 568,
    "max_y": 661
  },
  {
    "page_number": 176,
    "line_number": 6,
    "surah_number": 7,
    "ayah_number": 201,
    "position": 1,
    "min_x": 55,
    "max_x": 140,
    "min_y": 568,
    "max_y": 661
  },
  {
    "page_number": 176,
    "line_number": 7,
    "surah_number": 7,
    "ayah_number": 201,
    "position": 2,
    "min_x": 55,
    "max_x": 986,
    "min_y": 676,
    "max_y": 761
  },
  {
    "page_number": 176,
    "line_number": 8,
    "surah_number": 7,
    "ayah_number": 201,
    "position": 3,
    "min_x": 600,
    "max_x": 986,
    "min_y": 783,
    "max_y": 869
  },
  {
    "page_number": 176,
    "line_number": 8,
    "surah_number": 7,
    "ayah_number": 202,
    "position": 1,
    "min_x": 55,
    "max_x": 600,
    "min_y": 783,
    "max_y": 869
  },
  {
    "page_number": 176,
    "line_number": 9,
    "surah_number": 7,
    "ayah_number": 202,
    "position": 2,
    "min_x": 696,
    "max_x": 986,
    "min_y": 889,
    "max_y": 977
  },
  {
    "page_number": 176,
    "line_number": 9,
    "surah_number": 7,
    "ayah_number": 203,
    "position": 1,
    "min_x": 55,
    "max_x": 696,
    "min_y": 889,
    "max_y": 977
  },
  {
    "page_number": 176,
    "line_number": 10,
    "surah_number": 7,
    "ayah_number": 203,
    "position": 2,
    "min_x": 55,
    "max_x": 986,
    "min_y": 996,
    "max_y": 1082
  },
  {
    "page_number": 176,
    "line_number": 11,
    "surah_number": 7,
    "ayah_number": 203,
    "position": 3,
    "min_x": 424,
    "max_x": 986,
    "min_y": 1105,
    "max_y": 1187
  },
  {
    "page_number": 176,
    "line_number": 11,
    "surah_number": 7,
    "ayah_number": 204,
    "position": 1,
    "min_x": 55,
    "max_x": 424,
    "min_y": 1105,
    "max_y": 1187
  },
  {
    "page_number": 176,
    "line_number": 12,
    "surah_number": 7,
    "ayah_number": 204,
    "position": 2,
    "min_x": 277,
    "max_x": 986,
    "min_y": 1207,
    "max_y": 1295
  },
  {
    "page_number": 176,
    "line_number": 12,
    "surah_number": 7,
    "ayah_number": 205,
    "position": 1,
    "min_x": 55,
    "max_x": 277,
    "min_y": 1207,
    "max_y": 1295
  },
  {
    "page_number": 176,
    "line_number": 13,
    "surah_number": 7,
    "ayah_number": 205,
    "position": 2,
    "min_x": 55,
    "max_x": 986,
    "min_y": 1321,
    "max_y": 1401
  },
  {
    "page_number": 176,
    "line_number": 14,
    "surah_number": 7,
    "ayah_number": 205,
    "position": 3,
    "min_x": 410,
    "max_x": 986,
    "min_y": 1425,
    "max_y": 1507
  },
  {
    "page_number": 176,
    "line_number": 14,
    "surah_number": 7,
    "ayah_number": 206,
    "position": 1,
    "min_x": 55,
    "max_x": 410,
    "min_y": 1425,
    "max_y": 1507
  },
  {
    "page_number": 176,
    "line_number": 15,
    "surah_number": 7,
    "ayah_number": 206,
    "position": 2,
    "min_x": 55,
    "max_x": 986,
    "min_y": 1533,
    "max_y": 1614
  }
]