[
  {
    "page_number": 342,
    "line_number": 1,
    "surah_number": 23,
    "ayah_number": 1,
    "position": 1,
    "min_x": 614,
    "max_x": 994,
    "min_y": 115,
    "max_y": 209
  },
  {
    "page_number": 342,
    "line_number": 1,
    "surah_number": 23,
    "ayah_number": 2,
    "position": 1,
    "min_x": 42,
    "max_x": 614,
    "min_y": 115,
    "max_y": 209
  },
  {
    "page_number": 342,
    "line_number": 2,
    "surah_number": 23,
    "ayah_number": 3,
    "position": 1,
    "min_x": 362,
    "max_x": 994,
    "min_y": 219,
    "max_y": 316
  },
  {
    "page_number": 342,
    "line_number": 2,
    "surah_number": 23,
    "ayah_number": 4,
    "position": 1,
    "min_x": 42,
    "max_x": 362,
    "min_y": 219,
    "max_y": 316
  },
  {
    "page_number": 342,
    "line_number": 3,
    "surah_number": 23,
    "ayah_number": 4,
    "position": 2,
    "min_x": 767,
    "max_x": 994,
    "min_y": 326,
    "max_y": 427
  },
  {
    "page_number": 342,
    "line_number": 3,
    "surah_number": 23,
    "ayah_number": 5,
    "position": 1,
    "min_x": 170,
    "max_x": 767,
    "min_y": 326,
    "max_y": 427
  },
  {
    "page_number": 342,
    "line_number": 3,
    "surah_number": 23,
    "ayah_number": 6,
    "position": 1,
    "min_x": 42,
    "max_x": 170,
    "min_y": 326,
    "max_y": 427
  },
  {
    "page_number": 342,
    "line_number": 4,
    "surah_number": 23,
    "ayah_number": 6,
    "position": 2,
    "min_x": 42,
    "max_x": 994,
    "min_y": 438,
    "max_y": 532
  },
  {
    "page_number": 342,
    "line_number": 5,
    "surah_number": 23,
    "ayah_number": 7,
    "position": 1,
    "min_x": 212,
    "max_x": 994,
    "min_y": 535,
    "max_y": 633
  },
  {
    "page_number": 342,
    "line_number": 5,
    "surah_number": 23,
    "ayah_number": 8,
    "position": 1,
    "min_x": 42,
    "max_x": 212,
    "min_y": 535,
    "max_y": 633
  },
  {
    "page_number": 342,
    "line_number": 6,
    "surah_number": 23,
    "ayah_number": 8,
    "position": 2,
    "min_x": 444,
    "max_x": 994,
    "min_y": 648,
    "max_y": 742
  },
  {
    "page_number": 342,
    "line_number": 6,
    "surah_number": 23,
    "ayah_number": 9,
    "position": 1,
    "min_x": 42,
    "max_x": 444,
    "min_y": 648,
    "max_y": 742
  },
  {
    "page_number": 342,
    "line_number": 7,
    "surah_number": 23,
    "ayah_number": 9,
    "position": 2,
    "min_x": 736,
    "max_x": 994,
    "min_y": 752,
    "max_y": 849
  },
  {
    "page_number": 342,
    "line_number": 7,
    "surah_number": 23,
    "ayah_number": 10,
    "position": 1,
    "min_x": 325,
    "max_x": 736,
    "min_y": 752,
    "max_y": 849
  },
  {
    "page_number": 342,
    "line_number": 7,
    "surah_number": 23,
    "ayah_number": 11,
    "position": 1,
    "min_x": 42,
    "max_x": 325,
    "min_y": 752,
    "max_y": 849
  },
  {
    "page_number": 342,
    "line_number": 8,
    "surah_number": 23,
    "ayah_number": 11,
    "position": 2,
    "min_x": 460,
    "max_x": 994,
    "min_y": 871,
    "max_y": 954
  },
  {
    "page_number": 342,
    "line_number": 8,
    "surah_number": 23,
    "ayah_number": 12,
    "position": 1,
    "min_x": 42,
    "max_x": 460,
    "min_y": 871,
    "max_y": 954
  },
  {
    "page_number": 342,
    "line_number": 9,
    "surah_number": 23,
    "ayah_number": 12,
    "position": 2,
    "min_x": 661,
    "max_x": 994,
    "min_y": 975,
    "max_y": 1066
  },
  {
    "page_number": 342,
    "line_number": 9,
    "surah_number": 23,
    "ayah_number": 13,
    "position": 1,
    "min_x": 85,
    "max_x": 661,
    "min_y": 975,
    "max_y": 1066
  },
  {
    "page_number": 342,
    "line_number": 9,
    "surah_number": 23,
    "ayah_number": 14,
    "position": 1,
    "min_x": 42,
    "max_x": 85,
    "min_y": 975,
    "max_y": 1066
  },
  {
    "page_number": 342,
    "line_number": 10,
    "surah_number": 23,
    "ayah_number": 14,
    "position": 2,
    "min_x": 42,
    "max_x": 994,
    "min_y": 1080,
    "max_y": 1147
  },
  {
    "page_number": 342,
    "line_number": 11,
    "surah_number": 23,
    "ayah_number": 14,
    "position": 3,
    "min_x": 42,
    "max_x": 994,
    "min_y": 1183,
    "max_y": 1261
  },
  {
    "page_number": 342,
    "line_number": 12,
    "surah_number": 23,
    "ayah_number": 14,
    "position": 4,
    "min_x": 351,
    "max_x": 994,
    "min_y": 1284,
    "max_y": 1385
  },
  {
    "page_number": 342,
    "line_number": 12,
    "surah_number": 23,
    "ayah_number": 15,
    "position": 1,
    "min_x": 42,
    "max_x": 351,
    "min_y": 1284,
    "max_y": 1385
  },
  {
    "page_number": 342,
    "line_number": 13,
    "surah_number": 23,
    "ayah_number": 15,
    "position": 2,
    "min_x": 783,
    "max_x": 994,
    "min_y": 1400,
    "max_y": 1488
  },
  {
    "page_number": 342,
    "line_number": 13,
    "surah_number": 23,
    "ayah_number": 16,
    "position": 1,
    "min_x": 162,
    "max_x": 783,
    "min_y": 1400,
    "max_y": 1488
  },
  {
    "page_number": 342,
    "line_number": 13,
    "surah_number": 23,
    "ayah_number": 17,
    "position": 1,
    "min_x": 42,
    "max_x": 162,
    "min_y": 1400,
    "max_y": 1488
  },
  {
    "page_number": 342,
    "line_number": 14,
    "surah_number": 23,
    "ayah_number": 17,
    "position": 2,
    "min_x": 42,
    "max_x": 994,
    "min_y": 1504,
    "max_y": 1599
  }
]