[
  {
    "page_number": 427,
    "line_number": 1,
    "surah_number": 33,
    "ayah_number": 63,
    "position": 1,
    "min_x": 54,
    "max_x": 986,
    "min_y": 26,
    "max_y": 121
  },
  {
    "page_number": 427,
    "line_number": 2,
    "surah_number": 33,
    "ayah_number": 63,
    "position": 2,
    "min_x": 477,
    "max_x": 986,
    "min_y": 142,
    "max_y": 229
  },
  {
    "page_number": 427,
    "line_number": 2,
    "surah_number": 33,
    "ayah_number": 64,
    "position": 1,
    "min_x": 54,
    "max_x": 477,
    "min_y": 142,
    "max_y": 229
  },
  {
    "page_number": 427,
    "line_number": 3,
    "surah_number": 33,
    "ayah_number": 64,
    "position": 2,
    "min_x": 728,
    "max_x": 986,
    "min_y": 240,
    "max_y": 340
  },
  {
    "page_number": 427,
    "line_number": 3,
    "surah_number": 33,
    "ayah_number": 65,
    "position": 1,
    "min_x": 54,
    "max_x": 728,
    "min_y": 240,
    "max_y": 340
  },
  {
    "page_number": 427,
    "line_number": 4,
    "surah_number": 33,
    "ayah_number": 65,
    "position": 2,
    "min_x": 893,
    "max_x": 986,
    "min_y": 360,
    "max_y": 453
  },
  {
    "page_number": 427,
    "line_number": 4,
    "surah_number": 33,
    "ayah_number": 66,
    "position": 1,
    "min_x": 54,
    "max_x": 893,
    "min_y": 360,
    "max_y": 453
  },
  {
    "page_number": 427,
    "line_number": 5,
    "surah_number": 33,
    "ayah_number": 66,
    "position": 2,
    "min_x": 640,
    "max_x": 986,
    "min_y": 463,
    "max_y": 544
  },
  {
    "page_number": 427,
    "line_number": 5,
    "surah_number": 33,
    "ayah_number": 67,
    "position": 1,
    "min_x": 54,
    "max_x": 640,
    "min_y": 463,
    "max_y": 544
  },
  {
    "page_number": 427,
    "line_number": 6,
    "surah_number": 33,
    "ayah_number": 67,
    "position": 2,
    "min_x": 594,
    "max_x": 986,
    "min_y": 564,
    "max_y": 664
  },
  {
    "page_number": 427,
    "line_number": 6,
    "surah_number": 33,
    "ayah_number": 68,
    "position": 1,
    "min_x": 54,
    "max_x": 594,
    "min_y": 564,
    "max_y": 664
  },
  {
    "page_number": 427,
    "line_number": 7,
    "surah_number": 33,
    "ayah_number": 68,
    "position": 2,
    "min_x": 607,
    "max_x": 986,
    "min_y": 675,
    "max_y": 769
  },
  {
    "page_number": 427,
    "line_number": 7,
    "surah_number": 33,
    "ayah_number": 69,
    "position": 1,
    "min_x": 54,
    "max_x": 607,
    "min_y": 675,
    "max_y": 769
  },
  {
    "page_number": 427,
    "line_number": 8,
    "surah_number": 33,
    "ayah_number": 69,
    "position": 2,
    "min_x": 54,
    "max_x": 986,
    "min_y": 775,
    "max_y": 871
  },
  {
    "page_number": 427,
    "line_number": 9,
    "surah_number": 33,
    "ayah_number": 70,
    "position": 1,
    "min_x": 159,
    "max_x": 986,
    "min_y": 889,
    "max_y": 982
  },
  {
    "page_number": 427,
    "line_number": 9,
    "surah_number": 33,
    "ayah_number": 71,
    "position": 1,
    "min_x": 54,
    "max_x": 159,
    "min_y": 889,
    "max_y": 982
  },
  {
    "page_number": 427,
    "line_number": 10,
    "surah_number": 33,
    "ayah_number": 71,
    "position": 2,
    "min_x": 54,
    "max_x": 986,
    "min_y": 995,
    "max_y": 1093
  },
  {
    "page_number": 427,
    "line_number": 11,
    "surah_number": 33,
    "ayah_number": 71,
    "position": 3,
    "min_x": 569,
    "max_x": 986,
    "min_y": 1103,
    "max_y": 1186
  },
  {
    "page_number": 427,
    "line_number": 11,
    "surah_number": 33,
    "ayah_number": 72,
    "position": 1,
    "min_x": 54,
    "max_x": 569,
    "min_y": 1103,
    "max_y": 1186
  },
  {
    "page_number": 427,
    "line_number": 12,
    "surah_number": 33,
    "ayah_number": 72,
    "position": 2,
    "min_x": 54,
    "max_x": 986,
    "min_y": 1214,
    "max_y": 1293
  },
  {
    "page_number": 427,
    "line_number": 13,
    "surah_number": 33,
    "ayah_number": 72,
    "position": 3,
    "min_x": 407,
    "max_x": 986,
    "min_y": 1310,
    "max_y": 1406
  },
  {
    "page_number": 427,
    "line_number": 13,
    "surah_number": 33,
    "ayah_number": 73,
    "position": 1,
    "min_x": 54,
    "max_x": 407,
    "min_y": 1310,
    "max_y": 1406
  },
  {
    "page_number": 427,
    "line_number": 14,
    "surah_number": 33,
    "ayah_number": 73,
    "position": 2,
    "min_x": 54,
    "max_x": 986,
    "min_y": 1431,
    "max_y": 1514
  },
  {
    "page_number": 427,
    "line_number": 15,
    "surah_number": 33,
    "ayah_number": 73,
    "position": 3,
    "min_x": 54,
    "max_x": 986,
    "min_y": 1531,
    "max_y": 1613
  }
]